pure_cv/__init__.py
pure_cv/__init__.pyi
pure_cv/boxes.py
pure_cv/encoding.py
pure_cv/misc.py
pure_cv/opencv.py
pure_cv/plot.py
pure_cv/rescaling.py
pure_cv/rotation.py
pure_cv/types_.py
pure_cv/corners/__init__.py
pure_cv/corners/__init__.pyi
pure_cv/corners/transform.py
pure_cv/draw/__init__.py
pure_cv/draw/draw.py
pure_cv-0.2.7.dist-info/METADATA
pure_cv-0.2.7.dist-info/WHEEL
pure_cv-0.2.7.dist-info/top_level.txt
pure_cv-0.2.7.dist-info/RECORD
