Metadata-Version: 2.1
Name: pure-cv
Version: 0.2.7
Summary: Purely functional tools for Python OpenCV 
Author-email: Marcel Claramunt <marcel@moveread.com>
Requires-Python: >=3.10
Requires-Dist: ramda
Requires-Dist: numpy
Requires-Dist: opencv-python
Requires-Dist: lazy-loader
Requires-Dist: jaxtyping
Requires-Dist: nudantic
Provides-Extra: plot
Requires-Dist: matplotlib; extra == "plot"
